README.md
setup.py
infi/__init__.py
infi.dtypes.nqn.egg-info/PKG-INFO
infi.dtypes.nqn.egg-info/SOURCES.txt
infi.dtypes.nqn.egg-info/dependency_links.txt
infi.dtypes.nqn.egg-info/namespace_packages.txt
infi.dtypes.nqn.egg-info/not-zip-safe
infi.dtypes.nqn.egg-info/top_level.txt
infi/dtypes/__init__.py
infi/dtypes/nqn/__init__.py
infi/dtypes/nqn/__version__.py