Metadata-Version: 1.1
Name: infi.dtypes.nqn
Version: 0.1.0
Summary: Datatype for NQN
Home-page: https://github.com/infinidat/infi.dtypes.nqn
Author: Leonid Genkin
Author-email: lgenkin@infinidat.com
License: PSF
Platform: UNKNOWN
Classifier: Programming Language :: Python :: 2.7
Classifier: Programming Language :: Python :: 3.4
Classifier: Programming Language :: Python :: 3.5
Classifier: Programming Language :: Python :: 3.6
